pycat/__init__.py
pycat/pycat.py
filecat-0.0.1.dist-info/METADATA
filecat-0.0.1.dist-info/WHEEL
filecat-0.0.1.dist-info/entry_points.txt
filecat-0.0.1.dist-info/top_level.txt
filecat-0.0.1.dist-info/RECORD
