Metadata-Version: 2.1
Name: filecat
Version: 0.0.1
Summary: Utility program similar to cat
Home-page: https://github.com/rahuldshetty
Author: Rahul D Shetty
Author-email: 35rdshetty@gmail.com
License: UNKNOWN
Platform: UNKNOWN
